infomaniakclient/__init__.py
infomaniakclient/api.py
infomaniakclient-0.0.3.dist-info/LICENSE
infomaniakclient-0.0.3.dist-info/METADATA
infomaniakclient-0.0.3.dist-info/WHEEL
infomaniakclient-0.0.3.dist-info/top_level.txt
infomaniakclient-0.0.3.dist-info/RECORD
