Metadata-Version: 2.1
Name: infomaniakclient
Version: 0.0.3
Summary: Infomaniak Newsletter API client
Home-page: https://github.com/Potrac/infomaniakclient
Author: Potrac Grognuz
Author-email: potrac@grognuz.site
License: UNKNOWN
Keywords: infomaniak newsletter api client
Platform: UNKNOWN
Classifier: Programming Language :: Python :: 3
Classifier: License :: OSI Approved :: MIT License
Classifier: Operating System :: OS Independent
Requires-Dist: requests
